edith_pyaf/.DS_Store
edith_pyaf/__init__.py
edith_pyaf/diag.py
edith_pyaf/dynamics.py
edith_pyaf/extra.py
edith_pyaf/fit.py
edith_pyaf/glob.py
edith_pyaf/hams.py
edith_pyaf/initialize.py
edith_pyaf/input.dat
edith_pyaf/input.py
edith_pyaf/input_output.py
edith_pyaf/obs.py
edith_pyaf/parameter_scan.py
edith_pyaf/run.py
edith_pyaf/symm.py
edith_pyaf/templates/__init__.py
edith_pyaf/templates/input.dat
edith_pyaf/tests.py
edith_pyaf/utils.py
edith_pyaf/viz.py
edith_pyaf-0.1.4.dist-info/METADATA
edith_pyaf-0.1.4.dist-info/WHEEL
edith_pyaf-0.1.4.dist-info/RECORD
