Metadata-Version: 2.1
Name: edith-pyaf
Version: 0.1.4
Summary: Exact Diagonalization of Interacting Time-dependent Hamiltonians (in PYthon And Fortran)
License: GNU General Public License
Author: Paolo Molignini
Author-email: moligninip@gmail.com
Requires-Python: >=3.10
Classifier: License :: Other/Proprietary License
Classifier: Programming Language :: Python :: 3
Classifier: Programming Language :: Python :: 3.10
Classifier: Programming Language :: Python :: 3.11
Requires-Dist: matplotlib (>=3.7.1)
Requires-Dist: numpy (>=1.24.1)
Requires-Dist: pre-commit (>=2.16.0,<3.0.0)
Requires-Dist: scipy (>=1.10.0)
Requires-Dist: seaborn (>=0.11.2,<0.12.0)
Requires-Dist: setuptools (>=65.5.0)
Requires-Dist: tqdm (>=4.66.1)
